make_c/__about__.py
make_c/__init__.py
make_c/editors.py
make_c/environment.py
make_c/make_c.py
make_c/meta.py
make_c/version.py
make_c-0.2.0.dist-info/LICENSE
make_c-0.2.0.dist-info/METADATA
make_c-0.2.0.dist-info/WHEEL
make_c-0.2.0.dist-info/entry_points.txt
make_c-0.2.0.dist-info/top_level.txt
make_c-0.2.0.dist-info/RECORD
