Metadata-Version: 2.1
Name: make_c
Version: 0.2.0
Summary: A utility to create a simple C source file with a main and open it in an editor.
Home-page: https://github.com/zcutlip/make_c_program
Author: Zachary Cutlip
Author-email: uid000@gmail.com
License: MIT
Requires-Python: >=3.3
License-File: LICENSE
